starsign/__init__.py
starsign/starsign.py
starsign/test_suite.py
starsign-1.0.2.dist-info/LICENSE
starsign-1.0.2.dist-info/METADATA
starsign-1.0.2.dist-info/WHEEL
starsign-1.0.2.dist-info/top_level.txt
starsign-1.0.2.dist-info/RECORD
